retort/__init__.py
retort/cmd_helper.py
retort/command.py
retort/constant.py
retort/error.py
retort/migration.py
retort/data/retort_conf_example.py.txt
retort-0.1.0.dist-info/DESCRIPTION.rst
retort-0.1.0.dist-info/METADATA
retort-0.1.0.dist-info/RECORD
retort-0.1.0.dist-info/WHEEL
retort-0.1.0.dist-info/entry_points.txt
retort-0.1.0.dist-info/metadata.json
retort-0.1.0.dist-info/top_level.txt
