Metadata-Version: 2.0
Name: retort
Version: 0.1.0
Summary: Retort is a schema migration tool for SQLAlchemy.
Home-page: https://github.com/tpdn/retort
Author: NAKAMORI Ryosuke
Author-email: me@tpdn.kim
License: BSD License (2-Clause)
Keywords: SQLAlchemy migrations
Platform: UNKNOWN
Classifier: Programming Language :: Python
Classifier: Programming Language :: Python :: 3
Classifier: Programming Language :: Python :: 3.3
Classifier: Programming Language :: Python :: 3.4
Classifier: Programming Language :: Python :: 3.5
Classifier: Programming Language :: Python :: 3.6
Classifier: License :: OSI Approved :: BSD License
Classifier: Development Status :: 4 - Beta
Classifier: Intended Audience :: Developers
Classifier: Environment :: Console
Classifier: Topic :: Database :: Front-Ends
Requires-Python: >=3.3
Requires-Dist: SQLAlchemy
Requires-Dist: alembic
Requires-Dist: autopep8
